{
  "tenantId": "pb.newabadijatouli",
  "moduleName": "egov-location",
  "TenantBoundary": [
    {
      "hierarchyType": {
        "code": "REVENUE",
        "name": "REVENUE"
      },
      "boundary": {
        "id": 1,
        "boundaryNum": 1,
        "name": "NEW ABADI JATOULI",
        "localname": "NEW ABADI JATOULI",
        "longitude": null,
        "latitude": null,
        "label": "City",
        "code": "pb.newabadijatouli",
        "children":[
          {
            "id": 1,
            "boundaryNum": 1,
            "name": "NEW ABADI JATOULI",
            "localname": "NEW ABADI JATOULI",
            "longitude": null,
            "latitude": null,
            "label": "Locality",
            "code": "WARD1"
          }
        ]
      }
    },
    {
      "hierarchyType": {
        "code": "ADMIN",
        "name": "ADMIN"
      },
      "boundary": {
        "id": 1,
        "boundaryNum": 1,
        "name": "NEW ABADI JATOULI",
        "localname": "NEW ABADI JATOULI",
        "longitude": null,
        "latitude": null,
        "label": "City",
        "code": "pb.newabadijatouli",
        "children":[
          {
            "id": 1,
            "boundaryNum": 1,
            "name": "NEW ABADI JATOULI",
            "localname": "NEW ABADI JATOULI",
            "longitude": null,
            "latitude": null,
            "label": "Locality",
            "code": "WARD1"
          }
        ]
      }
    }
  ]
}
